reformat_rsem.py
reformat_rsem-0.0.1.dist-info/METADATA
reformat_rsem-0.0.1.dist-info/WHEEL
reformat_rsem-0.0.1.dist-info/licenses/LICENSE
reformat_rsem-0.0.1.dist-info/RECORD
